{
  "lead_id": "borbirosag-etterem-budapest",
  "business_name": "Borbíróság Étterem",
  "city": "Budapest",
  "prepared_at": "2026-06-27T09:51:03.945Z",
  "email_to": "+36 30 123 4567",
  "subject": "Weboldal ajánlat - Borbíróság Étterem",
  "body": "Kedves Borbíróság Étterem csapata!\n\nÉszrevettem, hogy a Borbíróság Étterem-nak még nincs modern weboldala.\n\nModern, mobilbarát weboldalakat készítek restaurant vállalkozásoknak Magyarországon.\n\nKészítettem egy egyedi előnézetet - kötelezettség nélkül.\n\n\n\nNyitottak lennének egy gyors 15 perces Google Meet beszélgetésre?\n\nÜdvözlettel,\nAI Web Agency\ntamerlan858@gmail.com",
  "attachments": {
    "website_preview": "projects/borbirosag-etterem/index.html",
    "diagnosis_report": "database/diagnosis/borbirosag-etterem.json"
  },
  "status": "ready_to_send"
}